cipher_zm2383/__init__.py
cipher_zm2383/cipher_zm2383.py
cipher_zm2383-0.1.3.dist-info/WHEEL
cipher_zm2383-0.1.3.dist-info/METADATA
cipher_zm2383-0.1.3.dist-info/RECORD
