Metadata-Version: 2.1
Name: cipher-zm2383
Version: 0.1.3
Summary: hm07
License: None
Author: Zhenwei Ma
Requires-Python: >=3.9,<4.0
Classifier: License :: Other/Proprietary License
Classifier: Programming Language :: Python :: 3
Classifier: Programming Language :: Python :: 3.9
Requires-Dist: pandas (>=1.3.4,<2.0.0)
